DLMS_SPODES_communications/__init__.py
DLMS_SPODES_communications/base.py
DLMS_SPODES_communications/ble.py
DLMS_SPODES_communications/network.py
DLMS_SPODES_communications/serial_port.py
dlms_spodes_communications-1.5.4.dist-info/METADATA
dlms_spodes_communications-1.5.4.dist-info/WHEEL
dlms_spodes_communications-1.5.4.dist-info/entry_points.txt
dlms_spodes_communications-1.5.4.dist-info/top_level.txt
dlms_spodes_communications-1.5.4.dist-info/RECORD
