Metadata-Version: 2.4
Name: DLMS_SPODES_communications
Version: 1.5.4
Summary: dlms-spodes
Author-email: Serj Kotilevski <youserj@outlook.com>
Project-URL: Source, https://github.com/youserj/DLMSSPODEScommunication_prj
Keywords: dlms,drivers
Classifier: Programming Language :: Python :: 3
Classifier: License :: OSI Approved :: MIT License
Classifier: Operating System :: OS Independent
Requires-Python: >=3.12
Requires-Dist: bleak>=0.22.3
Requires-Dist: pyserial-asyncio>=0.6
Requires-Dist: StructResult<0.10,>=0.9.5
Provides-Extra: dev
Requires-Dist: build>=1.2; extra == "dev"
Requires-Dist: twine>=6; extra == "dev"
Requires-Dist: mypy>=1.5.0; extra == "dev"
Requires-Dist: ruff>=0.11; extra == "dev"
Requires-Dist: types-requests; extra == "dev"
